<?xml version="1.0" encoding="utf-8"?>
<odoo>

<!--    &lt;!&ndash; Inherit Form View to Modify it &ndash;&gt;-->
<!--    <record id="view_account_config_settings" model="ir.ui.view">-->
<!--        <field name="name">account voucher settings</field>-->
<!--        <field name="model">res.config.settings</field>-->
<!--        <field name="inherit_id" ref="account.res_config_settings_view_form"/>-->
<!--        <field name="arch" type="xml">-->
<!--&lt;!&ndash;            <group name="bank_cash" groups="account.group_account_user" position="after">&ndash;&gt;-->
<!--&lt;!&ndash;                <separator string="Vouchers" groups="account.group_account_user"/>&ndash;&gt;-->
<!--&lt;!&ndash;                    <group name="vouchers" groups="account.group_account_user">&ndash;&gt;-->
<!--&lt;!&ndash;                        <label for="id" string="Configuration"/>&ndash;&gt;-->
<!--&lt;!&ndash;                        <div name="group_voucher_product_based">&ndash;&gt;-->
<!--&lt;!&ndash;                            <field name="group_voucher_product_based" class="oe_inline"/>&ndash;&gt;-->
<!--&lt;!&ndash;                            <label for="group_voucher_product_based"/>&ndash;&gt;-->
<!--&lt;!&ndash;                        </div>&ndash;&gt;-->
<!--&lt;!&ndash;                    </group>&ndash;&gt;-->
<!--&lt;!&ndash;            </group>&ndash;&gt;-->
<!--        </field>-->
<!--    </record>-->

</odoo>